odoo/addons/ssi_hr/README.rst
odoo/addons/ssi_hr/__init__.py
odoo/addons/ssi_hr/__manifest__.py
odoo/addons/ssi_hr/hooks.py
odoo/addons/ssi_hr/menu.xml
odoo/addons/ssi_hr/migrations/14.0.3.0.0/post-migration.py
odoo/addons/ssi_hr/models/__init__.py
odoo/addons/ssi_hr/models/hr_employee.py
odoo/addons/ssi_hr/models/res_company.py
odoo/addons/ssi_hr/models/res_config_settings.py
odoo/addons/ssi_hr/security/ir.model.access.csv
odoo/addons/ssi_hr/security/ir_module_category_data.xml
odoo/addons/ssi_hr/security/res_group_data.xml
odoo/addons/ssi_hr/static/description/icon.png
odoo/addons/ssi_hr/views/hr_employee_views.xml
odoo/addons/ssi_hr/views/res_config_settings_views.xml
odoo14_addon_ssi_hr-14.0.3.2.0.dist-info/METADATA
odoo14_addon_ssi_hr-14.0.3.2.0.dist-info/WHEEL
odoo14_addon_ssi_hr-14.0.3.2.0.dist-info/top_level.txt
odoo14_addon_ssi_hr-14.0.3.2.0.dist-info/RECORD
